moolearn/__init__.py
moo_learn-0.0.0.dist-info/LICENSE
moo_learn-0.0.0.dist-info/METADATA
moo_learn-0.0.0.dist-info/WHEEL
moo_learn-0.0.0.dist-info/top_level.txt
moo_learn-0.0.0.dist-info/RECORD
