Metadata-Version: 2.1
Name: moo-learn
Version: 0.0.0
Summary: Collection of multi-objective optimization learning algorithms consistent with `scikit-learn` API.
Author-email: KSSK <kssk@pwr.edu.pl>
Project-URL: Homepage, https://github.com/w4k2
Classifier: Programming Language :: Python :: 3
Classifier: License :: OSI Approved :: MIT License
Classifier: Operating System :: OS Independent
Requires-Python: >=3.7
License-File: LICENSE
